setup.py
latex2sympy/__init__.py
latex2sympy/asciimath_printer.py
latex2sympy/process_latex.py
latex2sympy3.egg-info/PKG-INFO
latex2sympy3.egg-info/SOURCES.txt
latex2sympy3.egg-info/dependency_links.txt
latex2sympy3.egg-info/requires.txt
latex2sympy3.egg-info/top_level.txt