Metadata-Version: 1.0
Name: latex2sympy3
Version: 0.1.1
Summary: Sympy generator from LaTeX expressions.
Home-page: https://github.com/jackatbancast/latex2sympy
Author: jack
Author-email: jack@bancast.net
License: MIT
Platform: UNKNOWN
